{
  "summary": {
    "total_tests": 1,
    "passed_tests": 0,
    "failed_tests": 1,
    "skipped_tests": 0,
    "global_errors": 3,
    "analyzed_at": "2026-04-03T23:29:16.185364",
    "xml_file": "reports\\output.xml"
  },
  "global_errors": [
    {
      "time": "2026-04-03T23:23:31.827161",
      "level": "ERROR",
      "message": "Command failed (2): awk: cannot open /proc/99999/smaps (No such file or directory)\n"
    },
    {
      "time": "2026-04-03T23:23:31.828020",
      "level": "WARN",
      "message": "Stack filtering failed via awk. Falling back to full smaps download..."
    },
    {
      "time": "2026-04-03T23:23:31.838618",
      "level": "ERROR",
      "message": "Command failed (1): cat: /proc/99999/smaps: No such file or directory\n"
    }
  ],
  "failed_cases_analysis": [
    {
      "test_case": "单进程栈内存使用率测试",
      "suite": "Test Stack Usage",
      "source_file": "",
      "line_number": 18,
      "status": "FAIL",
      "error_message": "Failed to download smaps for PID 99999",
      "tags": [
        "production",
        "smoke",
        "stack"
      ],
      "analysis": "AI分析失败: AI调用失败，已重试3次: Connection error.",
      "analyzed_at": "2026-04-03T23:29:16.185343"
    }
  ]
}